pyaes256/__init__.py
pyavalanche/__init__.py
python_aes256-1.0.5.dist-info/LICENSE
python_aes256-1.0.5.dist-info/METADATA
python_aes256-1.0.5.dist-info/WHEEL
python_aes256-1.0.5.dist-info/top_level.txt
python_aes256-1.0.5.dist-info/RECORD
