Metadata-Version: 2.1
Name: python-aes256
Version: 1.0.5
Summary: ENCRYPT DECRYPT AES256
Home-page: https://github.com/PROJECT-OUTBOX/django_lib_aes256
Author-email: suratiwan03@gmail.com
License: UNKNOWN
Keywords: encrypt,decrypt,string,manipulation
Platform: UNKNOWN
Classifier: License :: OSI Approved :: MIT License
Classifier: Intended Audience :: Developers
Classifier: Programming Language :: Python :: 3 :: Only
